reddit_etl_abd/__init__.py
reddit_etl_abd/extract/__init__.py
reddit_etl_abd/extract/data_ingestion.py
reddit_etl_abd/includes/__init__.py
reddit_etl_abd/includes/functions.py
reddit_etl_abd/includes/vars.py
reddit_etl_abd/load/__init__.py
reddit_etl_abd/load/load_author_flair.py
reddit_etl_abd/load/load_awardings.py
reddit_etl_abd/load/load_gildings.py
reddit_etl_abd/load/load_popular.py
reddit_etl_abd/transform/__init__.py
reddit_etl_abd/transform/transform_author_flair.py
reddit_etl_abd/transform/transform_awardings.py
reddit_etl_abd/transform/transform_gildings.py
reddit_etl_abd/transform/transform_popular.py
reddit_etl_abd-0.0.6.dist-info/LICENSE
reddit_etl_abd-0.0.6.dist-info/METADATA
reddit_etl_abd-0.0.6.dist-info/WHEEL
reddit_etl_abd-0.0.6.dist-info/top_level.txt
reddit_etl_abd-0.0.6.dist-info/RECORD
