Metadata-Version: 2.1
Name: reddit_etl_abd
Version: 0.0.6
Summary: Reddit ETL Scripts
Author: Abdullah Durrani
Classifier: Programming Language :: Python :: 3
Classifier: License :: OSI Approved :: MIT License
Requires-Python: >=3.7
License-File: LICENSE
